pyparam/__init__.py
pyparam/__main__.py
pyparam/completer.py
pyparam/defaults.py
pyparam/exceptions.py
pyparam/help.py
pyparam/param.py
pyparam/params.py
pyparam/utils.py
pyparam-0.5.4.dist-info/METADATA
pyparam-0.5.4.dist-info/WHEEL
pyparam-0.5.4.dist-info/LICENSE
pyparam-0.5.4.dist-info/RECORD
