Metadata-Version: 2.1
Name: pyparam
Version: 0.5.4
Summary: Powerful parameter processing.
Home-page: https://github.com/pwwang/pyparam
License: MIT
Author: pwwang
Author-email: pwwang@pwwang.com
Requires-Python: >=3.7,<4.0
Classifier: License :: OSI Approved :: MIT License
Classifier: Programming Language :: Python :: 3
Classifier: Programming Language :: Python :: 3.7
Classifier: Programming Language :: Python :: 3.8
Classifier: Programming Language :: Python :: 3.9
Classifier: Programming Language :: Python :: 3.10
Classifier: Programming Language :: Python :: 3.11
Requires-Dist: diot (>=0.1,<0.2)
Requires-Dist: python-simpleconf (>=0.5,<0.6)
Requires-Dist: rich (>=13,<14)
Project-URL: Repository, https://github.com/pwwang/pyparam
